runpycode/__init__.py
runpycode/code.py
runpycode-0.1.1.dist-info/WHEEL
runpycode-0.1.1.dist-info/METADATA
runpycode-0.1.1.dist-info/RECORD
